Fusion/Fusion.py
Fusion/__init__.py
Fusion/Packages/__init__.py
Fusion/Packages/packager.py
Fusion/download/__init__.py
Fusion/download/downloader.py
Fusion/ui/__init__.py
Fusion/ui/menu.py
ufusion-1.1.2.dist-info/METADATA
ufusion-1.1.2.dist-info/WHEEL
ufusion-1.1.2.dist-info/entry_points.txt
ufusion-1.1.2.dist-info/top_level.txt
ufusion-1.1.2.dist-info/RECORD
