Metadata-Version: 2.1
Name: ufusion
Version: 1.1.2
Summary: UNKNOWN
Author: f09l
Author-email: fostn.contact@gmail.com
License: UNKNOWN
Platform: UNKNOWN
Requires-Dist: requests
Requires-Dist: colorama
Requires-Dist: blessed
